hm01/__init__.py
hm01/clusterers/abstract_clusterer.py
hm01/clusterers/ikc_wrapper.py
hm01/clusterers/leiden_wrapper.py
hm01/cm.py
hm01/context.py
hm01/graph.py
hm01/mincut.py
hm01/mincut_requirement.py
hm01/pruner.py
hm01/to_universal.py
third_party/ikc.py
connectivity_modifier-0.1.0b13.dist-info/entry_points.txt
connectivity_modifier-0.1.0b13.dist-info/METADATA
connectivity_modifier-0.1.0b13.dist-info/LICENSE
connectivity_modifier-0.1.0b13.dist-info/WHEEL
connectivity_modifier-0.1.0b13.dist-info/RECORD
