Metadata-Version: 2.1
Name: connectivity-modifier
Version: 0.1.0b13
Summary: connectivity modifier
Author: runeblaze
Author-email: runeblaze@excite.co.jp
Requires-Python: >=3.9,<4.0
Classifier: Programming Language :: Python :: 3
Classifier: Programming Language :: Python :: 3.9
Classifier: Programming Language :: Python :: 3.10
Classifier: Programming Language :: Python :: 3.11
Requires-Dist: HeapDict (>=1.0.1,<2.0.0)
Requires-Dist: colorama (>=0.4.5,<0.5.0)
Requires-Dist: coloredlogs (>=15.0.1,<16.0.0)
Requires-Dist: graphviz (>=0.20.1,<0.21.0)
Requires-Dist: jsonpickle (>=2.2.0,<3.0.0)
Requires-Dist: leidenalg (>=0.9.0,<0.10.0)
Requires-Dist: networkit (>=10.0,<11.0)
Requires-Dist: numpy (>=1.23.3,<2.0.0)
Requires-Dist: pandas (>=1.5.0,<2.0.0)
Requires-Dist: pytest (>=7.1.3,<8.0.0)
Requires-Dist: structlog (>=22.1.0,<23.0.0)
Requires-Dist: tomli (>=2.0.1,<3.0.0)
Requires-Dist: treeswift (>=1.1.28,<2.0.0)
Requires-Dist: typer (>=0.6.1,<0.7.0)
Requires-Dist: typing-extensions (>=4.4.0,<5.0.0)
